paiso/__init__.py
paiso/paiso.py
paiso-0.1.dist-info/LICENSE
paiso-0.1.dist-info/METADATA
paiso-0.1.dist-info/WHEEL
paiso-0.1.dist-info/top_level.txt
paiso-0.1.dist-info/RECORD
