Metadata-Version: 2.1
Name: paiso
Version: 0.1
Summary: Example to build paiso
Home-page: UNKNOWN
Author: RAKOTONIAINA Harry Yves
Author-email: iharrysh.rakotoniaina@gmail.com
License: Copyright (c) 2018 The Python Packaging Authority        
Platform: UNKNOWN
Classifier: Development Status :: 3 - Alpha
Classifier: Intended Audience :: Developers
Classifier: Programming Language :: Python :: 3.10
Classifier: Programming Language :: Python :: 3.11
Classifier: Topic :: Utilities
Requires-Python: >=3.10, <3.12
License-File: LICENSE
